matlab_runtime/__init__.py
matlab_runtime/_version.py
matlab_runtime/cli.py
matlab_runtime/impl.py
matlab_runtime/info.json
matlab_runtime/utils.py
matlab_runtime-0.0.6.dist-info/licenses/LICENSE
matlab_runtime-0.0.6.dist-info/METADATA
matlab_runtime-0.0.6.dist-info/WHEEL
matlab_runtime-0.0.6.dist-info/entry_points.txt
matlab_runtime-0.0.6.dist-info/top_level.txt
matlab_runtime-0.0.6.dist-info/RECORD
