Metadata-Version: 2.4
Name: matlab-runtime
Version: 0.0.6
Summary: Cross-platform installer for the MATLAB runtime
Author-email: Yael Balbastre <y.balbastre@ucl.ac.uk>
Maintainer-email: Yael Balbastre <y.balbastre@ucl.ac.uk>
License-Expression: MIT
Project-URL: Homepage, https://github.com/balbasty/matlab-runtime
Project-URL: Issues, https://github.com/balbasty/matlab-runtime/issues
Classifier: Operating System :: OS Independent
Classifier: Programming Language :: Python :: 3
Classifier: Intended Audience :: Science/Research
Requires-Python: >=3
License-File: LICENSE
Provides-Extra: test
Requires-Dist: pytest; extra == "test"
Dynamic: license-file
